tiferet/__init__.py
tiferet/assets/__init__.py
tiferet/assets/constants.py
tiferet/assets/exceptions.py
tiferet/clients/__init__.py
tiferet/clients/yaml.py
tiferet/commands/__init__.py
tiferet/commands/app.py
tiferet/commands/container.py
tiferet/commands/core.py
tiferet/commands/dependencies.py
tiferet/commands/error.py
tiferet/commands/feature.py
tiferet/commands/settings.py
tiferet/commands/static.py
tiferet/configs/__init__.py
tiferet/configs/logging.py
tiferet/configs/settings.py
tiferet/contexts/__init__.py
tiferet/contexts/app.py
tiferet/contexts/cache.py
tiferet/contexts/cli.py
tiferet/contexts/container.py
tiferet/contexts/error.py
tiferet/contexts/feature.py
tiferet/contexts/logging.py
tiferet/contexts/request.py
tiferet/contracts/__init__.py
tiferet/contracts/app.py
tiferet/contracts/cache.py
tiferet/contracts/cli.py
tiferet/contracts/config.py
tiferet/contracts/container.py
tiferet/contracts/error.py
tiferet/contracts/feature.py
tiferet/contracts/file.py
tiferet/contracts/logging.py
tiferet/contracts/settings.py
tiferet/data/__init__.py
tiferet/data/app.py
tiferet/data/cli.py
tiferet/data/container.py
tiferet/data/error.py
tiferet/data/feature.py
tiferet/data/logging.py
tiferet/data/settings.py
tiferet/handlers/__init__.py
tiferet/handlers/cli.py
tiferet/handlers/logging.py
tiferet/handlers/settings.py
tiferet/middleware/__init__.py
tiferet/middleware/csv.py
tiferet/middleware/file.py
tiferet/middleware/json.py
tiferet/middleware/yaml.py
tiferet/models/__init__.py
tiferet/models/app.py
tiferet/models/cli.py
tiferet/models/container.py
tiferet/models/error.py
tiferet/models/feature.py
tiferet/models/logging.py
tiferet/models/settings.py
tiferet/proxies/__init__.py
tiferet/proxies/csv/__init__.py
tiferet/proxies/csv/settings.py
tiferet/proxies/json/__init__.py
tiferet/proxies/json/app.py
tiferet/proxies/json/cli.py
tiferet/proxies/json/container.py
tiferet/proxies/json/error.py
tiferet/proxies/json/feature.py
tiferet/proxies/json/logging.py
tiferet-1.7.0.dist-info/licenses/LICENSE
tiferet-1.7.0.dist-info/METADATA
tiferet-1.7.0.dist-info/WHEEL
tiferet-1.7.0.dist-info/top_level.txt
tiferet-1.7.0.dist-info/RECORD
