Metadata-Version: 2.4
Name: tiferet
Version: 1.7.0
Summary: A multi-purpose application framework embodying beauty in form.
Author-email: "Andrew Shatz, Great Strength Systems" <andrew@greatstrength.me>
License: BSD-3-Clause
Project-URL: Homepage, https://github.com/greatstrength/tiferet
Project-URL: Repository, https://github.com/greatstrength/tiferet
Project-URL: Download, https://github.com/greatstrength/tiferet
Requires-Python: >=3.10
License-File: LICENSE
Requires-Dist: schematics>=2.1.1
Requires-Dist: pyyaml>=6.0.1
Requires-Dist: dependencies>=7.7.0
Provides-Extra: test
Requires-Dist: pytest>=8.3.3; extra == "test"
Requires-Dist: pytest_env>=1.1.5; extra == "test"
Dynamic: license-file
